LICENSE.txt
MANIFEST.in
README.rst
setup.py
ox_herd/__init__.py
ox_herd/settings.py
ox_herd.egg-info/PKG-INFO
ox_herd.egg-info/SOURCES.txt
ox_herd.egg-info/dependency_links.txt
ox_herd.egg-info/entry_points.txt
ox_herd.egg-info/requires.txt
ox_herd.egg-info/top_level.txt
ox_herd/core/__init__.py
ox_herd/core/health.py
ox_herd/core/login_stub.py
ox_herd/core/ox_run_db.py
ox_herd/core/ox_tasks.py
ox_herd/core/scheduling.py
ox_herd/core/simple_ox_tasks.py
ox_herd/core/plugins/__init__.py
ox_herd/core/plugins/base.py
ox_herd/core/plugins/example_psutil_plugin.py
ox_herd/core/plugins/manager.py
ox_herd/core/plugins/post_to_github_plugin.py
ox_herd/core/plugins/awstools_plugin/__init__.py
ox_herd/core/plugins/awstools_plugin/core.py
ox_herd/core/plugins/awstools_plugin/forms.py
ox_herd/core/plugins/awstools_plugin/test_awstools.py
ox_herd/core/plugins/pylint_plugin/__init__.py
ox_herd/core/plugins/pylint_plugin/core.py
ox_herd/core/plugins/pylint_plugin/forms.py
ox_herd/core/plugins/pytest_plugin/__init__.py
ox_herd/core/plugins/pytest_plugin/core.py
ox_herd/core/plugins/pytest_plugin/forms.py
ox_herd/core/utils/__init__.py
ox_herd/core/utils/ox_decs.py
ox_herd/core/utils/test_utils.py
ox_herd/scripts/__init__.py
ox_herd/scripts/schedule.py
ox_herd/scripts/serve_ox_herd.py
ox_herd/ui/__init__.py
ox_herd/ui/flask_web_ui/__init__.py
ox_herd/ui/flask_web_ui/ox_herd/__init__.py
ox_herd/ui/flask_web_ui/ox_herd/core.py
ox_herd/ui/flask_web_ui/ox_herd/helpers.py
ox_herd/ui/flask_web_ui/ox_herd/views.py
ox_herd/ui/flask_web_ui/ox_herd/web_tasks.py
ox_herd/ui/flask_web_ui/ox_herd/static/w3.css
ox_herd/ui/flask_web_ui/ox_herd/templates/cancel_job.html
ox_herd/ui/flask_web_ui/ox_herd/templates/cleanup_job.html
ox_herd/ui/flask_web_ui/ox_herd/templates/failed_job.html
ox_herd/ui/flask_web_ui/ox_herd/templates/generic_display.html
ox_herd/ui/flask_web_ui/ox_herd/templates/generic_error.html
ox_herd/ui/flask_web_ui/ox_herd/templates/generic_ox_task_result.html
ox_herd/ui/flask_web_ui/ox_herd/templates/job_info.html
ox_herd/ui/flask_web_ui/ox_herd/templates/launch_job.html
ox_herd/ui/flask_web_ui/ox_herd/templates/layout.html
