Metadata-Version: 2.4
Name: ox_herd
Version: 0.8.4
Summary: Tools for task automation, continous integration, and testing.
Home-page: http://github.com/aocks/ox_herd
Author: Emin Martinian
Author-email: emin.martinian@gmail.com
License: custom
Keywords: testing continuous integration
Classifier: Development Status :: 3 - Alpha
Classifier: Intended Audience :: Developers
Classifier: Programming Language :: Python :: 3
License-File: LICENSE.txt
Requires-Dist: pytest
Requires-Dist: pytest-xdist
Requires-Dist: xmltodict
Requires-Dist: eyap
Dynamic: author
Dynamic: author-email
Dynamic: classifier
Dynamic: description
Dynamic: home-page
Dynamic: keywords
Dynamic: license
Dynamic: license-file
Dynamic: requires-dist
Dynamic: summary
